asproxy/__init__.py
asproxy/__main__.py
asproxy/cli.py
asproxy/server.py
asproxy-0.1.0.dist-info/LICENSE
asproxy-0.1.0.dist-info/METADATA
asproxy-0.1.0.dist-info/WHEEL
asproxy-0.1.0.dist-info/entry_points.txt
asproxy-0.1.0.dist-info/top_level.txt
asproxy-0.1.0.dist-info/RECORD
