Metadata-Version: 2.1
Name: asproxy
Version: 0.1.0
Summary: Simple HTTP proxy.
Home-page: https://github.com/nnnewb/asproxy
Author: weak_ptr
Author-email: weak_ptr@163.com
License: UNKNOWN
Keywords: proxy asyncio
Platform: UNKNOWN
Requires-Python: >= 3.6
Requires-Dist: aiohttp (==3.5.4)
Requires-Dist: coloredlogs (==10.0)
